konnect/curl/__init__.py
konnect/curl/_enums.py
konnect/curl/_exceptions.py
konnect/curl/_multi.py
konnect/curl/abc.py
konnect/curl/py.typed
konnect/curl/requests.py
konnect/curl/certificates/__init__.py
konnect/curl/certificates/ascii_armor.py
konnect/curl/certificates/configure.py
konnect/curl/certificates/detect.py
konnect/curl/certificates/encodings.py
konnect/curl/certificates/files.py
konnect_curl-0.2.3.dist-info/licenses/LICENCE.txt
konnect_curl-0.2.3.dist-info/WHEEL
konnect_curl-0.2.3.dist-info/METADATA
konnect_curl-0.2.3.dist-info/RECORD
